LICENSE
MANIFEST.in
README.rst
setup.py
django_xmpp.egg-info/PKG-INFO
django_xmpp.egg-info/SOURCES.txt
django_xmpp.egg-info/dependency_links.txt
django_xmpp.egg-info/not-zip-safe
django_xmpp.egg-info/requires.txt
django_xmpp.egg-info/top_level.txt
xmpp/__init__.py
xmpp/admin.py
xmpp/client.py
xmpp/models.py
xmpp/tests.py
xmpp/urls.py
xmpp/utils.py
xmpp/views.py
xmpp/management/__init__.py
xmpp/management/commands/__init__.py
xmpp/management/commands/ejabberd_auth.py
xmpp/static/css/converse.min.css
xmpp/static/fonticons/selection.json
xmpp/static/fonticons/style.css
xmpp/static/fonticons/fonts/icomoon.eot
xmpp/static/fonticons/fonts/icomoon.svg
xmpp/static/fonticons/fonts/icomoon.ttf
xmpp/static/fonticons/fonts/icomoon.woff
xmpp/static/images/arrow.svg
xmpp/static/images/bgbl.svg
xmpp/static/images/bgtr.svg
xmpp/static/images/bitcoin_qr_code.png
xmpp/static/images/dark-arrow.svg
xmpp/static/images/favicon.ico
xmpp/static/images/header.jpg
xmpp/static/images/overlay.png
xmpp/static/images/user.png
xmpp/static/js/converse.min.js
xmpp/static/js/converse_functions.js
xmpp/static/js/locales.js
xmpp/static/sounds/msg_received.mp3
xmpp/static/sounds/msg_received.ogg
xmpp/templates/conversejs_initialize.html
xmpp/templatetags/__init__.py
xmpp/templatetags/xmpp_tags.py