Metadata-Version: 1.1
Name: django-xmpp
Version: 0.4
Summary: XMPP integration for Django app made simple
Home-page: https://github.com/fpytloun/django-xmpp
Author: Filip Pytloun
Author-email: filip@pytloun.cz
License: GPLv2
Keywords: django xmpp conversejs jabber chat ejabberd
Platform: UNKNOWN
Classifier: Development Status :: 4 - Beta
Classifier: Environment :: Web Environment
Classifier: Framework :: Django
Classifier: Framework :: Django :: 1.8
Classifier: Intended Audience :: Developers
Classifier: License :: OSI Approved :: GNU General Public License v2 (GPLv2)
Classifier: Operating System :: OS Independent
Classifier: Programming Language :: Python
Classifier: Programming Language :: Python :: 2
Classifier: Programming Language :: Python :: 2.7
